{
    "name": "Learning",
    "skillMetadata": {
        "sections": [
            {
                "name": "Fallback option",
                "fields": [
                    {
                        "name": "enable_fallback_ex",
                        "type": "checkbox",
                        "label": "enable fallback",
                        "value": "True",
                        "placeholder": "demo prompt in the input box"
                    },
                    {
                        "name": "allow_category_ex",
                        "type": "text",
                        "label": "allow category current humor, love, science",
                        "value": "humor, love, science"
                    }
                ]
            },
            {
                "name": "Path of the data",
                "fields": [
                    {
                        "type": "label",
                        "label": "path for storing the learning questions. leave empty for default"
                    },
                    {
                        "name": "public_path_ex",
                        "type": "text",
                        "label": "public path",
                        "value": ""
                    },
                    {
                        "name": "local_path_ex",
                        "type": "text",
                        "label": "internel path",
                        "value": ""
                    }
                ]
            }
        ]
    }
}
